urwid/__init__.py
urwid/_async_kw_event_loop.py
urwid/canvas.py
urwid/command_map.py
urwid/compat.py
urwid/container.py
urwid/curses_display.py
urwid/decoration.py
urwid/display_common.py
urwid/escape.py
urwid/font.py
urwid/graphics.py
urwid/html_fragment.py
urwid/lcd_display.py
urwid/listbox.py
urwid/main_loop.py
urwid/monitored_list.py
urwid/numedit.py
urwid/old_str_util.py
urwid/raw_display.py
urwid/signals.py
urwid/split_repr.py
urwid/str_util.cp311-win_amd64.pyd
urwid/text_layout.py
urwid/treetools.py
urwid/util.py
urwid/version.py
urwid/vterm.py
urwid/web_display.py
urwid/widget.py
urwid/wimp.py
urwid/win32.py
urwid/tests/__init__.py
urwid/tests/test_canvas.py
urwid/tests/test_container.py
urwid/tests/test_decoration.py
urwid/tests/test_doctests.py
urwid/tests/test_escapes.py
urwid/tests/test_event_loops.py
urwid/tests/test_graphics.py
urwid/tests/test_listbox.py
urwid/tests/test_str_util.py
urwid/tests/test_text_layout.py
urwid/tests/test_util.py
urwid/tests/test_vterm.py
urwid/tests/test_widget.py
urwid/tests/util.py
urwid_mitmproxy-2.1.2.1.dist-info/COPYING
urwid_mitmproxy-2.1.2.1.dist-info/METADATA
urwid_mitmproxy-2.1.2.1.dist-info/WHEEL
urwid_mitmproxy-2.1.2.1.dist-info/top_level.txt
urwid_mitmproxy-2.1.2.1.dist-info/RECORD
